{
  "tables": [
    {
      "name": "event_speaker",
      "columns": [
        {
          "name": "id",
          "type": "Unknown",
          "primaryKey": true
        },
        {
          "name": "event_id",
          "type": "Unknown",
          "primaryKey": true,
          "foreignKey": true
        },
        {
          "name": "company",
          "type": "Unknown"
        },
        {
          "name": "description",
          "type": "Unknown"
        },
        {
          "name": "first_name",
          "type": "Unknown"
        },
        {
          "name": "last_name",
          "type": "Unknown"
        },
        {
          "name": "linkedin_url",
          "type": "Unknown"
        },
        {
          "name": "profile_picture_url",
          "type": "Unknown"
        },
        {
          "name": "title",
          "type": "Unknown"
        },
        {
          "name": "twitter_url",
          "type": "Unknown"
        }
      ],
      "tags": [],
      "link": "https://customapi.goldcast.io/swagger-ui/#/Public%20APIs%20for%20Registration%20Page/Speakers%20public%20v1"
    },
    {
      "name": "event_public_agenda_session_speaker",
      "columns": [
        {
          "name": "event_id",
          "type": "Unknown",
          "primaryKey": true,
          "foreignKey": true
        },
        {
          "name": "id",
          "type": "Unknown",
          "primaryKey": true,
          "foreignKey": true
        },
        {
          "name": "session_id",
          "type": "Unknown",
          "primaryKey": true,
          "foreignKey": true
        }
      ],
      "tags": [],
      "link": "https://customapi.goldcast.io/swagger-ui/#/Public%20APIs%20for%20Registration%20Page/Agenda%20public%20v1"
    },
    {
      "name": "event_public_agenda",
      "columns": [
        {
          "name": "session_id",
          "type": "Unknown",
          "primaryKey": true
        },
        {
          "name": "event_id",
          "type": "Unknown",
          "primaryKey": true,
          "foreignKey": true
        },
        {
          "name": "session_description",
          "type": "Unknown"
        },
        {
          "name": "session_end_time",
          "type": "Unknown"
        },
        {
          "name": "session_location",
          "type": "Unknown"
        },
        {
          "name": "session_name",
          "type": "Unknown"
        },
        {
          "name": "session_start_time",
          "type": "Unknown"
        },
        {
          "name": "session_type",
          "type": "Unknown"
        }
      ],
      "tags": [],
      "link": "https://customapi.goldcast.io/swagger-ui/#/Public%20APIs%20for%20Registration%20Page/Agenda%20public%20v1"
    },
    {
      "name": "ticket_type",
      "columns": [
        {
          "name": "id",
          "type": "Unknown",
          "primaryKey": true
        },
        {
          "name": "event_id",
          "type": "Unknown",
          "primaryKey": true,
          "foreignKey": true
        },
        {
          "name": "allow_all_tracks",
          "type": "Unknown"
        },
        {
          "name": "category_name",
          "type": "Unknown"
        },
        {
          "name": "category_ref_id",
          "type": "Unknown"
        },
        {
          "name": "code",
          "type": "Unknown"
        },
        {
          "name": "created_at",
          "type": "Unknown"
        },
        {
          "name": "label",
          "type": "Unknown"
        },
        {
          "name": "member_count",
          "type": "Unknown"
        },
        {
          "name": "ticket_type_id",
          "type": "Unknown"
        },
        {
          "name": "updated_at",
          "type": "Unknown"
        }
      ],
      "tags": [],
      "link": "https://customapi.goldcast.io/swagger-ui/#/Ticket%20type/List%20ticket%20type"
    },
    {
      "name": "agenda_item",
      "columns": [
        {
          "name": "id",
          "type": "Unknown",
          "primaryKey": true
        },
        {
          "name": "event_id",
          "type": "Unknown",
          "foreignKey": true
        },
        {
          "name": "allowed_end_time",
          "type": "Unknown"
        },
        {
          "name": "allowed_start_time",
          "type": "Unknown"
        },
        {
          "name": "description",
          "type": "Unknown"
        },
        {
          "name": "end_time",
          "type": "Unknown"
        },
        {
          "name": "expected_end_time",
          "type": "Unknown"
        },
        {
          "name": "is_live",
          "type": "Unknown"
        },
        {
          "name": "kind",
          "type": "Unknown"
        },
        {
          "name": "live_end_time",
          "type": "Unknown"
        },
        {
          "name": "live_start_time",
          "type": "Unknown"
        },
        {
          "name": "start_time",
          "type": "Unknown"
        },
        {
          "name": "title",
          "type": "Unknown"
        }
      ],
      "tags": [],
      "link": "https://customapi.goldcast.io/swagger-ui/#/Agenda%20item/List%20agenda%20item"
    },
    {
      "name": "event_supported_language",
      "columns": [
        {
          "name": "index",
          "type": "Unknown",
          "primaryKey": true
        },
        {
          "name": "event_id",
          "type": "Unknown",
          "primaryKey": true,
          "foreignKey": true
        },
        {
          "name": "code",
          "type": "Unknown"
        },
        {
          "name": "name",
          "type": "Unknown"
        },
        {
          "name": "native_name",
          "type": "Unknown"
        }
      ],
      "tags": [],
      "link": "https://customapi.goldcast.io/swagger-ui/#/Event/List%20events"
    },
    {
      "name": "event_form_field",
      "columns": [
        {
          "name": "id",
          "type": "Unknown",
          "primaryKey": true
        },
        {
          "name": "event_id",
          "type": "Unknown",
          "primaryKey": true,
          "foreignKey": true
        },
        {
          "name": "checked",
          "type": "Unknown"
        },
        {
          "name": "custom_validation_regex",
          "type": "Unknown"
        },
        {
          "name": "error",
          "type": "Unknown"
        },
        {
          "name": "error_message",
          "type": "Unknown"
        },
        {
          "name": "is_standard",
          "type": "Unknown"
        },
        {
          "name": "mapped_title",
          "type": "Unknown"
        },
        {
          "name": "optional",
          "type": "Unknown"
        },
        {
          "name": "title",
          "type": "Unknown"
        },
        {
          "name": "type",
          "type": "Unknown"
        },
        {
          "name": "value",
          "type": "Unknown"
        }
      ],
      "tags": [],
      "link": "https://customapi.goldcast.io/swagger-ui/#/Event/List%20events"
    },
    {
      "name": "event",
      "columns": [
        {
          "name": "id",
          "type": "Unknown",
          "primaryKey": true
        },
        {
          "name": "organization",
          "type": "Unknown",
          "foreignKey": true
        },
        {
          "name": "broadcast_filler_image_s_3_path",
          "type": "Unknown"
        },
        {
          "name": "broadcast_filler_video_s_3_path",
          "type": "Unknown"
        },
        {
          "name": "broadcast_type",
          "type": "Unknown"
        },
        {
          "name": "created_at",
          "type": "Unknown"
        },
        {
          "name": "created_by",
          "type": "Unknown"
        },
        {
          "name": "created_by_user_first_name",
          "type": "Unknown"
        },
        {
          "name": "created_by_user_id",
          "type": "Unknown"
        },
        {
          "name": "created_by_user_last_name",
          "type": "Unknown"
        },
        {
          "name": "created_by_user_organization",
          "type": "Unknown"
        },
        {
          "name": "created_by_user_profile_picture_url",
          "type": "Unknown"
        },
        {
          "name": "created_by_user_role",
          "type": "Unknown"
        },
        {
          "name": "default_language_dropdown_enabled",
          "type": "Unknown"
        },
        {
          "name": "deleted",
          "type": "Unknown"
        },
        {
          "name": "deleted_by_cascade",
          "type": "Unknown"
        },
        {
          "name": "end_time",
          "type": "Unknown"
        },
        {
          "name": "event_type",
          "type": "Unknown"
        },
        {
          "name": "integration_config_updated_salesforce",
          "type": "Unknown"
        },
        {
          "name": "is_blueprint",
          "type": "Unknown"
        },
        {
          "name": "is_hybrid",
          "type": "Unknown"
        },
        {
          "name": "manual_breakout",
          "type": "Unknown"
        },
        {
          "name": "meta_tag",
          "type": "Json"
        },
        {
          "name": "owner",
          "type": "Unknown"
        },
        {
          "name": "recording_state",
          "type": "Unknown"
        },
        {
          "name": "registrant_count",
          "type": "Unknown"
        },
        {
          "name": "registration_cta_link",
          "type": "Unknown"
        },
        {
          "name": "registration_form_form_type",
          "type": "Unknown"
        },
        {
          "name": "registration_form_id",
          "type": "Unknown"
        },
        {
          "name": "registration_form_is_default",
          "type": "Unknown"
        },
        {
          "name": "registration_form_is_global_form",
          "type": "Unknown"
        },
        {
          "name": "registration_form_is_one_click_enabled",
          "type": "Unknown"
        },
        {
          "name": "registration_form_name",
          "type": "Unknown"
        },
        {
          "name": "registration_form_organization",
          "type": "Unknown"
        },
        {
          "name": "registration_form_schema_url",
          "type": "Unknown"
        },
        {
          "name": "series_attendee_count",
          "type": "Unknown"
        },
        {
          "name": "series_blueprint_event",
          "type": "Unknown"
        },
        {
          "name": "series_builder_html",
          "type": "Unknown"
        },
        {
          "name": "series_builder_raw_json",
          "type": "Unknown"
        },
        {
          "name": "series_contains_waitlist_event",
          "type": "Unknown"
        },
        {
          "name": "series_created_at",
          "type": "Unknown"
        },
        {
          "name": "series_created_by",
          "type": "Unknown"
        },
        {
          "name": "series_description",
          "type": "Unknown"
        },
        {
          "name": "series_email_alias_name",
          "type": "Unknown"
        },
        {
          "name": "series_end_date_threshold",
          "type": "Unknown"
        },
        {
          "name": "series_favicon",
          "type": "Unknown"
        },
        {
          "name": "series_frequency",
          "type": "Unknown"
        },
        {
          "name": "series_id",
          "type": "Unknown"
        },
        {
          "name": "series_initial_event_generated",
          "type": "Unknown"
        },
        {
          "name": "series_initial_event_generation_count",
          "type": "Unknown"
        },
        {
          "name": "series_last_synced_at",
          "type": "Unknown"
        },
        {
          "name": "series_marketing_tags",
          "type": "Unknown"
        },
        {
          "name": "series_marketo_base_program_id",
          "type": "Unknown"
        },
        {
          "name": "series_marketo_program_folder_id",
          "type": "Unknown"
        },
        {
          "name": "series_marketo_program_folder_name",
          "type": "Unknown"
        },
        {
          "name": "series_marketo_settings",
          "type": "Unknown"
        },
        {
          "name": "series_marketo_status",
          "type": "Unknown"
        },
        {
          "name": "series_name",
          "type": "Unknown"
        },
        {
          "name": "series_next_event_generation_time",
          "type": "Unknown"
        },
        {
          "name": "series_organization",
          "type": "Unknown"
        },
        {
          "name": "series_parent",
          "type": "Unknown"
        },
        {
          "name": "series_registrant_count",
          "type": "Unknown"
        },
        {
          "name": "series_registration_form",
          "type": "Unknown"
        },
        {
          "name": "series_registration_form_data",
          "type": "Unknown"
        },
        {
          "name": "series_registration_form_form_type",
          "type": "Unknown"
        },
        {
          "name": "series_registration_form_id",
          "type": "Unknown"
        },
        {
          "name": "series_registration_form_is_default",
          "type": "Unknown"
        },
        {
          "name": "series_registration_form_is_global_form",
          "type": "Unknown"
        },
        {
          "name": "series_registration_form_is_one_click_enabled",
          "type": "Unknown"
        },
        {
          "name": "series_registration_form_name",
          "type": "Unknown"
        },
        {
          "name": "series_registration_form_organization",
          "type": "Unknown"
        },
        {
          "name": "series_registration_form_schema_url",
          "type": "Unknown"
        },
        {
          "name": "series_registration_form_url",
          "type": "Unknown"
        },
        {
          "name": "series_repeating_event_sync_allowed",
          "type": "Unknown"
        },
        {
          "name": "series_schedule",
          "type": "Unknown"
        },
        {
          "name": "series_schedule_status",
          "type": "Json"
        },
        {
          "name": "series_social_media_image",
          "type": "Unknown"
        },
        {
          "name": "series_sync_id",
          "type": "Unknown"
        },
        {
          "name": "series_sync_status",
          "type": "Unknown"
        },
        {
          "name": "series_tags",
          "type": "Json"
        },
        {
          "name": "series_total_event_threshold",
          "type": "Unknown"
        },
        {
          "name": "series_type",
          "type": "Unknown"
        },
        {
          "name": "series_unit",
          "type": "Unknown"
        },
        {
          "name": "series_upcoming_event_count",
          "type": "Unknown"
        },
        {
          "name": "series_updated_at",
          "type": "Unknown"
        },
        {
          "name": "series_updated_by",
          "type": "Unknown"
        },
        {
          "name": "series_url",
          "type": "Unknown"
        },
        {
          "name": "series_workspace",
          "type": "Unknown"
        },
        {
          "name": "short_id",
          "type": "Unknown"
        },
        {
          "name": "splash_tracking_pixel_snippet_body_section_script",
          "type": "Unknown"
        },
        {
          "name": "splash_tracking_pixel_snippet_created_at",
          "type": "Unknown"
        },
        {
          "name": "splash_tracking_pixel_snippet_created_by",
          "type": "Unknown"
        },
        {
          "name": "splash_tracking_pixel_snippet_custom_event_script",
          "type": "Unknown"
        },
        {
          "name": "splash_tracking_pixel_snippet_head_section_script",
          "type": "Unknown"
        },
        {
          "name": "splash_tracking_pixel_snippet_id",
          "type": "Unknown"
        },
        {
          "name": "splash_tracking_pixel_snippet_updated_at",
          "type": "Unknown"
        },
        {
          "name": "splash_tracking_pixel_snippet_updated_by",
          "type": "Unknown"
        },
        {
          "name": "start_time",
          "type": "Unknown"
        },
        {
          "name": "supported_captions_languages",
          "type": "Json"
        },
        {
          "name": "theme_alt_primary_background_shade",
          "type": "Unknown"
        },
        {
          "name": "theme_auth_theme",
          "type": "Unknown"
        },
        {
          "name": "theme_ctrl_bar_shade_alpha",
          "type": "Unknown"
        },
        {
          "name": "theme_event_background",
          "type": "Unknown"
        },
        {
          "name": "theme_font_link",
          "type": "Unknown"
        },
        {
          "name": "theme_font_name",
          "type": "Unknown"
        },
        {
          "name": "theme_font_src",
          "type": "Unknown"
        },
        {
          "name": "theme_font_type",
          "type": "Unknown"
        },
        {
          "name": "theme_logos",
          "type": "Unknown"
        },
        {
          "name": "theme_lower_third_background",
          "type": "Unknown"
        },
        {
          "name": "theme_lower_third_text_color",
          "type": "Unknown"
        },
        {
          "name": "theme_mobile_event_background",
          "type": "Unknown"
        },
        {
          "name": "theme_mobile_splash_page_hero",
          "type": "Unknown"
        },
        {
          "name": "theme_mobile_stage_background",
          "type": "Unknown"
        },
        {
          "name": "theme_name_card_background",
          "type": "Unknown"
        },
        {
          "name": "theme_name_card_radius",
          "type": "Unknown"
        },
        {
          "name": "theme_name_card_text_color",
          "type": "Unknown"
        },
        {
          "name": "theme_name_card_title_display",
          "type": "Unknown"
        },
        {
          "name": "theme_p_2_p_panel_shade_alpha",
          "type": "Unknown"
        },
        {
          "name": "theme_page_item_alpha",
          "type": "Unknown"
        },
        {
          "name": "theme_primary_background_shade",
          "type": "Unknown"
        },
        {
          "name": "theme_primary_color",
          "type": "Unknown"
        },
        {
          "name": "theme_primary_text_color",
          "type": "Unknown"
        },
        {
          "name": "theme_screen_saver_background",
          "type": "Unknown"
        },
        {
          "name": "theme_screen_saver_text_color",
          "type": "Unknown"
        },
        {
          "name": "theme_secondary_color",
          "type": "Unknown"
        },
        {
          "name": "theme_secondary_text_color",
          "type": "Unknown"
        },
        {
          "name": "theme_show_borders",
          "type": "Unknown"
        },
        {
          "name": "theme_sidebar_alpha",
          "type": "Unknown"
        },
        {
          "name": "theme_sidebar_blur",
          "type": "Unknown"
        },
        {
          "name": "theme_splash_background_color",
          "type": "Unknown"
        },
        {
          "name": "theme_splash_background_shade",
          "type": "Unknown"
        },
        {
          "name": "theme_splash_font_link",
          "type": "Unknown"
        },
        {
          "name": "theme_splash_font_name",
          "type": "Unknown"
        },
        {
          "name": "theme_splash_font_src",
          "type": "Unknown"
        },
        {
          "name": "theme_splash_font_type",
          "type": "Unknown"
        },
        {
          "name": "theme_splash_gradient_height",
          "type": "Unknown"
        },
        {
          "name": "theme_splash_page_hero",
          "type": "Unknown"
        },
        {
          "name": "theme_splash_shade_alpha",
          "type": "Unknown"
        },
        {
          "name": "theme_splash_text_color",
          "type": "Unknown"
        },
        {
          "name": "theme_splash_text_onimage_color",
          "type": "Unknown"
        },
        {
          "name": "theme_stage_background",
          "type": "Unknown"
        },
        {
          "name": "theme_stage_text_color",
          "type": "Unknown"
        },
        {
          "name": "theme_type",
          "type": "Unknown"
        },
        {
          "name": "theme_virtual_backgrounds",
          "type": "Unknown"
        },
        {
          "name": "timezone",
          "type": "Unknown"
        },
        {
          "name": "title",
          "type": "Unknown"
        },
        {
          "name": "updated_at",
          "type": "Instant"
        },
        {
          "name": "updated_by",
          "type": "Unknown"
        },
        {
          "name": "updated_by_user_email",
          "type": "Unknown"
        },
        {
          "name": "updated_by_user_first_name",
          "type": "Unknown"
        },
        {
          "name": "updated_by_user_id",
          "type": "Unknown"
        },
        {
          "name": "updated_by_user_last_name",
          "type": "Unknown"
        },
        {
          "name": "updated_by_user_organization",
          "type": "Unknown"
        },
        {
          "name": "updated_by_user_profile_picture_url",
          "type": "Unknown"
        },
        {
          "name": "updated_by_user_role",
          "type": "Unknown"
        },
        {
          "name": "vivenu_event_url",
          "type": "Unknown"
        },
        {
          "name": "workspace_color",
          "type": "Unknown"
        },
        {
          "name": "workspace_icon",
          "type": "Unknown"
        },
        {
          "name": "workspace_id",
          "type": "Unknown"
        },
        {
          "name": "workspace_name",
          "type": "Unknown"
        }
      ],
      "tags": [],
      "link": "https://customapi.goldcast.io/swagger-ui/#/Event/List%20events"
    },
    {
      "name": "track_allowed_ticket_type",
      "columns": [
        {
          "name": "ticket_type_id",
          "type": "Unknown",
          "primaryKey": true,
          "foreignKey": true
        },
        {
          "name": "track_id",
          "type": "Unknown",
          "primaryKey": true,
          "foreignKey": true
        }
      ],
      "tags": [],
      "link": "https://customapi.goldcast.io/swagger-ui/#/Broadcasts/List%20broadcasts"
    },
    {
      "name": "track",
      "columns": [
        {
          "name": "id",
          "type": "Unknown",
          "primaryKey": true
        },
        {
          "name": "event_id",
          "type": "Unknown",
          "foreignKey": true
        },
        {
          "name": "agenda_items",
          "type": "Unknown"
        },
        {
          "name": "channel_mmid",
          "type": "Unknown"
        },
        {
          "name": "created_at",
          "type": "Unknown"
        },
        {
          "name": "custom",
          "type": "Unknown"
        },
        {
          "name": "sort_priority",
          "type": "Unknown"
        },
        {
          "name": "title",
          "type": "Unknown"
        },
        {
          "name": "updated_at",
          "type": "Unknown"
        }
      ],
      "tags": [],
      "link": "https://customapi.goldcast.io/swagger-ui/#/Tracks/List%20tracks"
    },
    {
      "name": "organization",
      "columns": [
        {
          "name": "id",
          "type": "Unknown",
          "primaryKey": true
        },
        {
          "name": "allow_hybrid_events",
          "type": "Unknown"
        },
        {
          "name": "can_add_track",
          "type": "Unknown"
        },
        {
          "name": "can_change_event_length",
          "type": "Unknown"
        },
        {
          "name": "can_create_rtmp_broadcast",
          "type": "Unknown"
        },
        {
          "name": "content_clips_count",
          "type": "Unknown"
        },
        {
          "name": "content_lab_enabled",
          "type": "Unknown"
        },
        {
          "name": "content_video_duration",
          "type": "Unknown"
        },
        {
          "name": "created_at",
          "type": "Unknown"
        },
        {
          "name": "enable_live_captions",
          "type": "Unknown"
        },
        {
          "name": "enable_old_reg_pages",
          "type": "Unknown"
        },
        {
          "name": "enabled_rtmp_out",
          "type": "Unknown"
        },
        {
          "name": "in_person_events_enabled",
          "type": "Unknown"
        },
        {
          "name": "is_booths_tab_enabled",
          "type": "Unknown"
        },
        {
          "name": "is_content_lab_standalone",
          "type": "Unknown"
        },
        {
          "name": "is_kudo_enabled",
          "type": "Unknown"
        },
        {
          "name": "is_ux_translation_enabled",
          "type": "Unknown"
        },
        {
          "name": "is_webhook_enabled",
          "type": "Unknown"
        },
        {
          "name": "name",
          "type": "Unknown"
        },
        {
          "name": "no_of_organizer_seats",
          "type": "Unknown"
        },
        {
          "name": "owner",
          "type": "Unknown"
        },
        {
          "name": "short_name",
          "type": "Unknown"
        },
        {
          "name": "show_advanced_branding_tab",
          "type": "Unknown"
        },
        {
          "name": "show_forms",
          "type": "Unknown"
        },
        {
          "name": "show_secondary_booth_tab",
          "type": "Unknown"
        },
        {
          "name": "tier",
          "type": "Unknown"
        },
        {
          "name": "updated_at",
          "type": "Unknown"
        },
        {
          "name": "use_new_studio_app",
          "type": "Unknown"
        },
        {
          "name": "workspace_settings_count",
          "type": "Unknown"
        }
      ],
      "tags": [],
      "link": "https://customapi.goldcast.io/swagger-ui/#/Organization/List%20organization"
    },
    {
      "name": "booth_discussion_group",
      "columns": [
        {
          "name": "id",
          "type": "Unknown",
          "primaryKey": true
        },
        {
          "name": "booth_id",
          "type": "Unknown",
          "primaryKey": true,
          "foreignKey": true
        },
        {
          "name": "event_id",
          "type": "Unknown",
          "foreignKey": true
        },
        {
          "name": "capacity",
          "type": "Unknown"
        },
        {
          "name": "created_at",
          "type": "Unknown"
        },
        {
          "name": "current",
          "type": "Unknown"
        },
        {
          "name": "deleted",
          "type": "Unknown"
        },
        {
          "name": "deleted_by_cascade",
          "type": "Unknown"
        },
        {
          "name": "description",
          "type": "Unknown"
        },
        {
          "name": "ends_at",
          "type": "Unknown"
        },
        {
          "name": "is_booth",
          "type": "Unknown"
        },
        {
          "name": "is_breakout",
          "type": "Unknown"
        },
        {
          "name": "is_live",
          "type": "Unknown"
        },
        {
          "name": "mmid",
          "type": "Unknown"
        },
        {
          "name": "moderator",
          "type": "Json"
        },
        {
          "name": "owner",
          "type": "Unknown"
        },
        {
          "name": "participants",
          "type": "Json"
        },
        {
          "name": "rank",
          "type": "Unknown"
        },
        {
          "name": "recording_directory",
          "type": "Unknown"
        },
        {
          "name": "recording_resourceid",
          "type": "Unknown"
        },
        {
          "name": "recording_sid",
          "type": "Unknown"
        },
        {
          "name": "shadow_mmid",
          "type": "Unknown"
        },
        {
          "name": "sponsor_image",
          "type": "Unknown"
        },
        {
          "name": "starts_at",
          "type": "Unknown"
        },
        {
          "name": "title",
          "type": "Unknown"
        },
        {
          "name": "updated_at",
          "type": "Unknown"
        },
        {
          "name": "video_quality",
          "type": "Unknown"
        }
      ],
      "tags": [],
      "link": "https://customapi.goldcast.io/swagger-ui/#/Booths/List%20booths"
    },
    {
      "name": "booth_resource",
      "columns": [
        {
          "name": "id",
          "type": "Unknown",
          "primaryKey": true
        },
        {
          "name": "booth_id",
          "type": "Unknown",
          "primaryKey": true,
          "foreignKey": true
        },
        {
          "name": "event_id",
          "type": "Unknown",
          "foreignKey": true
        },
        {
          "name": "content_object",
          "type": "Unknown"
        },
        {
          "name": "content_type",
          "type": "Unknown"
        },
        {
          "name": "created_at",
          "type": "Unknown"
        },
        {
          "name": "key_or_url",
          "type": "Unknown"
        },
        {
          "name": "name",
          "type": "Unknown"
        },
        {
          "name": "object_id",
          "type": "Unknown"
        },
        {
          "name": "s_3_hosted",
          "type": "Unknown"
        },
        {
          "name": "updated_at",
          "type": "Unknown"
        }
      ],
      "tags": [],
      "link": "https://customapi.goldcast.io/swagger-ui/#/Booths/List%20booths"
    },
    {
      "name": "booth",
      "columns": [
        {
          "name": "id",
          "type": "Unknown",
          "primaryKey": true
        },
        {
          "name": "event_id",
          "type": "Unknown",
          "foreignKey": true
        },
        {
          "name": "booth_type",
          "type": "Unknown"
        },
        {
          "name": "cover_image",
          "type": "Unknown"
        },
        {
          "name": "description",
          "type": "Unknown"
        },
        {
          "name": "hyperlink",
          "type": "Unknown"
        },
        {
          "name": "logo",
          "type": "Unknown"
        },
        {
          "name": "title",
          "type": "Unknown"
        }
      ],
      "tags": [],
      "link": "https://customapi.goldcast.io/swagger-ui/#/Booths/List%20booths"
    },
    {
      "name": "broadcast_speaker",
      "columns": [
        {
          "name": "broadcast_id",
          "type": "Unknown",
          "primaryKey": true,
          "foreignKey": true
        },
        {
          "name": "event_id",
          "type": "Unknown",
          "primaryKey": true,
          "foreignKey": true
        },
        {
          "name": "speaker_id",
          "type": "Unknown",
          "primaryKey": true,
          "foreignKey": true
        }
      ],
      "tags": [],
      "link": "https://customapi.goldcast.io/swagger-ui/#/Broadcasts/List%20broadcasts"
    },
    {
      "name": "broadcast_video_asset",
      "columns": [
        {
          "name": "id",
          "type": "Unknown",
          "primaryKey": true
        },
        {
          "name": "broadcast_id",
          "type": "Unknown",
          "primaryKey": true,
          "foreignKey": true
        },
        {
          "name": "event_id",
          "type": "Unknown",
          "primaryKey": true,
          "foreignKey": true
        },
        {
          "name": "asset_type",
          "type": "Unknown"
        },
        {
          "name": "client_hls_path",
          "type": "Unknown"
        },
        {
          "name": "created_at",
          "type": "Unknown"
        },
        {
          "name": "created_by_email",
          "type": "Unknown"
        },
        {
          "name": "created_by_first_name",
          "type": "Unknown"
        },
        {
          "name": "created_by_id",
          "type": "Unknown"
        },
        {
          "name": "created_by_last_name",
          "type": "Unknown"
        },
        {
          "name": "created_by_organization",
          "type": "Unknown"
        },
        {
          "name": "created_by_profile_picture_url",
          "type": "Unknown"
        },
        {
          "name": "created_by_role",
          "type": "Unknown"
        },
        {
          "name": "creation_type",
          "type": "Unknown"
        },
        {
          "name": "deleted",
          "type": "Unknown"
        },
        {
          "name": "deleted_by_cascade",
          "type": "Unknown"
        },
        {
          "name": "duration",
          "type": "Unknown"
        },
        {
          "name": "embedded_url",
          "type": "Unknown"
        },
        {
          "name": "fallback_hls_path",
          "type": "Unknown"
        },
        {
          "name": "hls_path",
          "type": "Unknown"
        },
        {
          "name": "hls_url",
          "type": "Json"
        },
        {
          "name": "metadata",
          "type": "Json"
        },
        {
          "name": "name",
          "type": "Unknown"
        },
        {
          "name": "onedrive_file_id",
          "type": "Unknown"
        },
        {
          "name": "onedrive_upload_state",
          "type": "Unknown"
        },
        {
          "name": "organization",
          "type": "Unknown"
        },
        {
          "name": "path",
          "type": "Unknown"
        },
        {
          "name": "source",
          "type": "Unknown"
        },
        {
          "name": "thumbnail",
          "type": "Unknown"
        },
        {
          "name": "transcode_finish_time",
          "type": "Unknown"
        },
        {
          "name": "transcode_status",
          "type": "Unknown"
        },
        {
          "name": "transcoder_error",
          "type": "Json"
        },
        {
          "name": "transcoder_warning",
          "type": "Json"
        },
        {
          "name": "transcript_path",
          "type": "Json"
        },
        {
          "name": "updated_at",
          "type": "Unknown"
        },
        {
          "name": "updated_by_email",
          "type": "Unknown"
        },
        {
          "name": "updated_by_first_name",
          "type": "Unknown"
        },
        {
          "name": "updated_by_id",
          "type": "Unknown"
        },
        {
          "name": "updated_by_last_name",
          "type": "Unknown"
        },
        {
          "name": "updated_by_organization",
          "type": "Unknown"
        },
        {
          "name": "updated_by_profile_picture_url",
          "type": "Unknown"
        },
        {
          "name": "updated_by_role",
          "type": "Unknown"
        },
        {
          "name": "uploaded",
          "type": "Unknown"
        },
        {
          "name": "video_usage_count",
          "type": "Unknown"
        },
        {
          "name": "workspace",
          "type": "Unknown"
        }
      ],
      "tags": [],
      "link": "https://customapi.goldcast.io/swagger-ui/#/Broadcasts/List%20broadcasts"
    },
    {
      "name": "broadcast",
      "columns": [
        {
          "name": "event_id",
          "type": "Unknown",
          "primaryKey": true
        },
        {
          "name": "id",
          "type": "Unknown",
          "primaryKey": true
        },
        {
          "name": "organization",
          "type": "Unknown",
          "foreignKey": true
        },
        {
          "name": "allowed_end_time",
          "type": "Unknown"
        },
        {
          "name": "allowed_start_time",
          "type": "Unknown"
        },
        {
          "name": "created_at",
          "type": "Unknown"
        },
        {
          "name": "deleted",
          "type": "Unknown"
        },
        {
          "name": "deleted_by_cascade",
          "type": "Unknown"
        },
        {
          "name": "end_time",
          "type": "Unknown"
        },
        {
          "name": "expected_end_time",
          "type": "Unknown"
        },
        {
          "name": "have_polls",
          "type": "Unknown"
        },
        {
          "name": "manual_redirection_enabled",
          "type": "Unknown"
        },
        {
          "name": "medialive_rtmp_input_channel_id",
          "type": "Unknown"
        },
        {
          "name": "medialive_rtmp_input_channel_states",
          "type": "Unknown"
        },
        {
          "name": "medialive_rtmp_input_created_at",
          "type": "Unknown"
        },
        {
          "name": "medialive_rtmp_input_event_id",
          "type": "Unknown"
        },
        {
          "name": "medialive_rtmp_input_failover_in_stream_key",
          "type": "Unknown"
        },
        {
          "name": "medialive_rtmp_input_failover_input_url",
          "type": "Unknown"
        },
        {
          "name": "medialive_rtmp_input_id",
          "type": "Unknown"
        },
        {
          "name": "medialive_rtmp_input_in_stream_key",
          "type": "Unknown"
        },
        {
          "name": "medialive_rtmp_input_input_frame_rate_alarm_state",
          "type": "Unknown"
        },
        {
          "name": "medialive_rtmp_input_input_frame_rate_alert_sent",
          "type": "Unknown"
        },
        {
          "name": "medialive_rtmp_input_input_url",
          "type": "Unknown"
        },
        {
          "name": "medialive_rtmp_input_name",
          "type": "Unknown"
        },
        {
          "name": "medialive_rtmp_input_network_in_alarm_state",
          "type": "Unknown"
        },
        {
          "name": "medialive_rtmp_input_network_in_alert_sent",
          "type": "Unknown"
        },
        {
          "name": "medialive_rtmp_input_output_url",
          "type": "Unknown"
        },
        {
          "name": "medialive_rtmp_input_test_run_end_time",
          "type": "Unknown"
        },
        {
          "name": "medialive_rtmp_input_updated_at",
          "type": "Unknown"
        },
        {
          "name": "mmid",
          "type": "Unknown"
        },
        {
          "name": "on_demand_asset_asset_type",
          "type": "Unknown"
        },
        {
          "name": "on_demand_asset_client_hls_path",
          "type": "Unknown"
        },
        {
          "name": "on_demand_asset_created_at",
          "type": "Unknown"
        },
        {
          "name": "on_demand_asset_created_by",
          "type": "Unknown"
        },
        {
          "name": "on_demand_asset_creation_type",
          "type": "Unknown"
        },
        {
          "name": "on_demand_asset_deleted",
          "type": "Unknown"
        },
        {
          "name": "on_demand_asset_deleted_by_cascade",
          "type": "Unknown"
        },
        {
          "name": "on_demand_asset_duration",
          "type": "Unknown"
        },
        {
          "name": "on_demand_asset_embedded_url",
          "type": "Unknown"
        },
        {
          "name": "on_demand_asset_fallback_hls_path",
          "type": "Unknown"
        },
        {
          "name": "on_demand_asset_hls_path",
          "type": "Unknown"
        },
        {
          "name": "on_demand_asset_id",
          "type": "Unknown"
        },
        {
          "name": "on_demand_asset_metadata",
          "type": "Json"
        },
        {
          "name": "on_demand_asset_name",
          "type": "Unknown"
        },
        {
          "name": "on_demand_asset_onedrive_file_id",
          "type": "Unknown"
        },
        {
          "name": "on_demand_asset_onedrive_upload_state",
          "type": "Unknown"
        },
        {
          "name": "on_demand_asset_organization",
          "type": "Unknown"
        },
        {
          "name": "on_demand_asset_path",
          "type": "Unknown"
        },
        {
          "name": "on_demand_asset_source",
          "type": "Unknown"
        },
        {
          "name": "on_demand_asset_thumbnail",
          "type": "Unknown"
        },
        {
          "name": "on_demand_asset_transcode_finish_time",
          "type": "Unknown"
        },
        {
          "name": "on_demand_asset_transcode_status",
          "type": "Unknown"
        },
        {
          "name": "on_demand_asset_transcoder_errors",
          "type": "Json"
        },
        {
          "name": "on_demand_asset_transcoder_type",
          "type": "Unknown"
        },
        {
          "name": "on_demand_asset_transcoder_warnings",
          "type": "Json"
        },
        {
          "name": "on_demand_asset_transcript_path",
          "type": "Unknown"
        },
        {
          "name": "on_demand_asset_updated_at",
          "type": "Unknown"
        },
        {
          "name": "on_demand_asset_updated_by",
          "type": "Unknown"
        },
        {
          "name": "on_demand_asset_uploaded",
          "type": "Unknown"
        },
        {
          "name": "on_demand_asset_urls",
          "type": "Unknown"
        },
        {
          "name": "on_demand_asset_video_usage_count",
          "type": "Unknown"
        },
        {
          "name": "on_demand_asset_workspace",
          "type": "Unknown"
        },
        {
          "name": "recording_individual_directory",
          "type": "Unknown"
        },
        {
          "name": "recording_individual_resource_id",
          "type": "Unknown"
        },
        {
          "name": "recording_individual_sid",
          "type": "Unknown"
        },
        {
          "name": "recording_mix_directory",
          "type": "Unknown"
        },
        {
          "name": "recording_mix_resource_id",
          "type": "Unknown"
        },
        {
          "name": "recording_mix_sid",
          "type": "Unknown"
        },
        {
          "name": "recording_video_asset_asset_type",
          "type": "Unknown"
        },
        {
          "name": "recording_video_asset_client_hls_path",
          "type": "Unknown"
        },
        {
          "name": "recording_video_asset_created_at",
          "type": "Unknown"
        },
        {
          "name": "recording_video_asset_created_by",
          "type": "Unknown"
        },
        {
          "name": "recording_video_asset_creation_type",
          "type": "Unknown"
        },
        {
          "name": "recording_video_asset_deleted",
          "type": "Unknown"
        },
        {
          "name": "recording_video_asset_deleted_by_cascade",
          "type": "Unknown"
        },
        {
          "name": "recording_video_asset_duration",
          "type": "Unknown"
        },
        {
          "name": "recording_video_asset_embedded_url",
          "type": "Unknown"
        },
        {
          "name": "recording_video_asset_fallback_hls_path",
          "type": "Unknown"
        },
        {
          "name": "recording_video_asset_hls_path",
          "type": "Unknown"
        },
        {
          "name": "recording_video_asset_id",
          "type": "Unknown"
        },
        {
          "name": "recording_video_asset_metadata",
          "type": "Json"
        },
        {
          "name": "recording_video_asset_name",
          "type": "Unknown"
        },
        {
          "name": "recording_video_asset_onedrive_file_id",
          "type": "Unknown"
        },
        {
          "name": "recording_video_asset_onedrive_upload_state",
          "type": "Unknown"
        },
        {
          "name": "recording_video_asset_organization",
          "type": "Unknown"
        },
        {
          "name": "recording_video_asset_path",
          "type": "Unknown"
        },
        {
          "name": "recording_video_asset_source",
          "type": "Unknown"
        },
        {
          "name": "recording_video_asset_thumbnail",
          "type": "Unknown"
        },
        {
          "name": "recording_video_asset_transcode_finish_time",
          "type": "Unknown"
        },
        {
          "name": "recording_video_asset_transcode_status",
          "type": "Unknown"
        },
        {
          "name": "recording_video_asset_transcoder_errors",
          "type": "Json"
        },
        {
          "name": "recording_video_asset_transcoder_type",
          "type": "Unknown"
        },
        {
          "name": "recording_video_asset_transcoder_warnings",
          "type": "Json"
        },
        {
          "name": "recording_video_asset_transcript_path",
          "type": "Unknown"
        },
        {
          "name": "recording_video_asset_updated_at",
          "type": "Unknown"
        },
        {
          "name": "recording_video_asset_updated_by",
          "type": "Unknown"
        },
        {
          "name": "recording_video_asset_uploaded",
          "type": "Unknown"
        },
        {
          "name": "recording_video_asset_urls",
          "type": "Unknown"
        },
        {
          "name": "recording_video_asset_video_usage_count",
          "type": "Unknown"
        },
        {
          "name": "recording_video_asset_workspace",
          "type": "Unknown"
        },
        {
          "name": "resources",
          "type": "Json"
        },
        {
          "name": "staffs",
          "type": "Json"
        },
        {
          "name": "start_time",
          "type": "Unknown"
        },
        {
          "name": "surveys",
          "type": "Json"
        },
        {
          "name": "ticker_url",
          "type": "Unknown"
        },
        {
          "name": "title",
          "type": "Unknown"
        },
        {
          "name": "updated_at",
          "type": "Unknown"
        }
      ],
      "tags": [],
      "link": "https://customapi.goldcast.io/swagger-ui/#/Broadcasts/List%20broadcasts"
    },
    {
      "name": "tag_library",
      "columns": [
        {
          "name": "id",
          "type": "Unknown",
          "primaryKey": true
        },
        {
          "name": "organization",
          "type": "Unknown",
          "foreignKey": true
        },
        {
          "name": "created_at",
          "type": "Unknown"
        },
        {
          "name": "created_by",
          "type": "Unknown"
        },
        {
          "name": "tag_name",
          "type": "Unknown"
        },
        {
          "name": "updated_by",
          "type": "Unknown"
        }
      ],
      "tags": [],
      "link": "https://customapi.goldcast.io/swagger-ui/#/Tag%20library/List%20tag%20library"
    },
    {
      "name": "event_member",
      "columns": [
        {
          "name": "id",
          "type": "Unknown",
          "primaryKey": true
        },
        {
          "name": "event_id",
          "type": "Unknown",
          "primaryKey": true,
          "foreignKey": true
        },
        {
          "name": "track_id",
          "type": "Unknown",
          "foreignKey": true
        },
        {
          "name": "created_at",
          "type": "Unknown"
        },
        {
          "name": "event_role",
          "type": "Unknown"
        },
        {
          "name": "event_role_list",
          "type": "Json"
        },
        {
          "name": "external_demo_requested",
          "type": "Unknown"
        },
        {
          "name": "external_demo_requested_at",
          "type": "Unknown"
        },
        {
          "name": "kind",
          "type": "Json"
        },
        {
          "name": "magic_link",
          "type": "Unknown"
        },
        {
          "name": "marketo_lead_id",
          "type": "Unknown"
        },
        {
          "name": "organization_user_address_line_2",
          "type": "Unknown"
        },
        {
          "name": "organization_user_age",
          "type": "Unknown"
        },
        {
          "name": "organization_user_allow_admin_panel_notifications",
          "type": "Unknown"
        },
        {
          "name": "organization_user_city",
          "type": "Unknown"
        },
        {
          "name": "organization_user_company",
          "type": "Unknown"
        },
        {
          "name": "organization_user_country",
          "type": "Unknown"
        },
        {
          "name": "organization_user_created_at",
          "type": "Unknown"
        },
        {
          "name": "organization_user_description",
          "type": "Unknown"
        },
        {
          "name": "organization_user_extra_data",
          "type": "Json"
        },
        {
          "name": "organization_user_first_name",
          "type": "Unknown"
        },
        {
          "name": "organization_user_id",
          "type": "Unknown"
        },
        {
          "name": "organization_user_industry",
          "type": "Unknown"
        },
        {
          "name": "organization_user_last_name",
          "type": "Unknown"
        },
        {
          "name": "organization_user_linkedin_url",
          "type": "Unknown"
        },
        {
          "name": "organization_user_location",
          "type": "Unknown"
        },
        {
          "name": "organization_user_organization",
          "type": "Unknown"
        },
        {
          "name": "organization_user_phone_number",
          "type": "Unknown"
        },
        {
          "name": "organization_user_profile_picture_url",
          "type": "Unknown"
        },
        {
          "name": "organization_user_state",
          "type": "Unknown"
        },
        {
          "name": "organization_user_street_address",
          "type": "Unknown"
        },
        {
          "name": "organization_user_title",
          "type": "Unknown"
        },
        {
          "name": "organization_user_twitter_url",
          "type": "Unknown"
        },
        {
          "name": "organization_user_updated_at",
          "type": "Unknown"
        },
        {
          "name": "organization_user_user",
          "type": "Unknown"
        },
        {
          "name": "organization_user_zip_code",
          "type": "Unknown"
        },
        {
          "name": "qrcode",
          "type": "Unknown"
        },
        {
          "name": "qrcode_encoding",
          "type": "Unknown"
        },
        {
          "name": "salesforce_member_id",
          "type": "Unknown"
        },
        {
          "name": "updated_at",
          "type": "Unknown"
        },
        {
          "name": "user_address_line_2",
          "type": "Unknown"
        },
        {
          "name": "user_age",
          "type": "Unknown"
        },
        {
          "name": "user_allow_admin_panel_notifications",
          "type": "Unknown"
        },
        {
          "name": "user_city",
          "type": "Unknown"
        },
        {
          "name": "user_company",
          "type": "Unknown"
        },
        {
          "name": "user_country",
          "type": "Unknown"
        },
        {
          "name": "user_description",
          "type": "Unknown"
        },
        {
          "name": "user_display_email",
          "type": "Unknown"
        },
        {
          "name": "user_email",
          "type": "Unknown"
        },
        {
          "name": "user_extra_data",
          "type": "Unknown"
        },
        {
          "name": "user_first_name",
          "type": "Unknown"
        },
        {
          "name": "user_id",
          "type": "Unknown"
        },
        {
          "name": "user_industry",
          "type": "Unknown"
        },
        {
          "name": "user_is_admin",
          "type": "Unknown"
        },
        {
          "name": "user_is_content_lab_standalone",
          "type": "Unknown"
        },
        {
          "name": "user_is_registered",
          "type": "Unknown"
        },
        {
          "name": "user_last_name",
          "type": "Unknown"
        },
        {
          "name": "user_linkedin_url",
          "type": "Unknown"
        },
        {
          "name": "user_location",
          "type": "Unknown"
        },
        {
          "name": "user_mmid",
          "type": "Unknown"
        },
        {
          "name": "user_organization",
          "type": "Unknown"
        },
        {
          "name": "user_phone_number",
          "type": "Unknown"
        },
        {
          "name": "user_profile_picture_url",
          "type": "Unknown"
        },
        {
          "name": "user_requester_role",
          "type": "Unknown"
        },
        {
          "name": "user_role",
          "type": "Unknown"
        },
        {
          "name": "user_state",
          "type": "Unknown"
        },
        {
          "name": "user_street_address",
          "type": "Unknown"
        },
        {
          "name": "user_title",
          "type": "Unknown"
        },
        {
          "name": "user_twitter_url",
          "type": "Unknown"
        },
        {
          "name": "user_zip_code",
          "type": "Unknown"
        },
        {
          "name": "uuid",
          "type": "Unknown"
        },
        {
          "name": "vivenu_ticket_url",
          "type": "Unknown"
        }
      ],
      "tags": [],
      "link": "https://customapi.goldcast.io/swagger-ui/#/Event%20members/List%20event%20members"
    },
    {
      "name": "resource",
      "columns": [
        {
          "name": "id",
          "type": "Unknown",
          "primaryKey": true
        },
        {
          "name": "event_id",
          "type": "Unknown",
          "foreignKey": true
        },
        {
          "name": "content_object",
          "type": "Unknown"
        },
        {
          "name": "content_type",
          "type": "Unknown"
        },
        {
          "name": "created_at",
          "type": "Unknown"
        },
        {
          "name": "key_or_url",
          "type": "Unknown"
        },
        {
          "name": "name",
          "type": "Unknown"
        },
        {
          "name": "object_id",
          "type": "Unknown"
        },
        {
          "name": "s_3_hosted",
          "type": "Unknown"
        },
        {
          "name": "updated_at",
          "type": "Unknown"
        }
      ],
      "tags": [],
      "link": "https://customapi.goldcast.io/swagger-ui/#/Resources/List%20resources"
    }
  ],
  "relations": [
    {
      "targetTable": "event",
      "sourceTable": "event_speaker",
      "targetColumns": [
        "id"
      ],
      "sourceColumns": [
        "event_id"
      ]
    },
    {
      "targetTable": "event_speaker",
      "sourceTable": "event_public_agenda_session_speaker",
      "targetColumns": [
        "id"
      ],
      "sourceColumns": [
        "id"
      ]
    },
    {
      "targetTable": "event_public_agenda",
      "sourceTable": "event_public_agenda_session_speaker",
      "targetColumns": [
        "session_id"
      ],
      "sourceColumns": [
        "session_id"
      ]
    },
    {
      "targetTable": "event_public_agenda",
      "sourceTable": "event_public_agenda_session_speaker",
      "targetColumns": [
        "event_id"
      ],
      "sourceColumns": [
        "event_id"
      ]
    },
    {
      "targetTable": "event",
      "sourceTable": "event_public_agenda",
      "targetColumns": [
        "id"
      ],
      "sourceColumns": [
        "event_id"
      ]
    },
    {
      "targetTable": "event",
      "sourceTable": "ticket_type",
      "targetColumns": [
        "id"
      ],
      "sourceColumns": [
        "event_id"
      ]
    },
    {
      "targetTable": "event",
      "sourceTable": "agenda_item",
      "targetColumns": [
        "id"
      ],
      "sourceColumns": [
        "event_id"
      ]
    },
    {
      "targetTable": "event",
      "sourceTable": "event_supported_language",
      "targetColumns": [
        "id"
      ],
      "sourceColumns": [
        "event_id"
      ]
    },
    {
      "targetTable": "event",
      "sourceTable": "event_form_field",
      "targetColumns": [
        "id"
      ],
      "sourceColumns": [
        "event_id"
      ]
    },
    {
      "targetTable": "organization",
      "sourceTable": "event",
      "targetColumns": [
        "id"
      ],
      "sourceColumns": [
        "organization"
      ]
    },
    {
      "targetTable": "ticket_type",
      "sourceTable": "track_allowed_ticket_type",
      "targetColumns": [
        "id"
      ],
      "sourceColumns": [
        "ticket_type_id"
      ]
    },
    {
      "targetTable": "track",
      "sourceTable": "track_allowed_ticket_type",
      "targetColumns": [
        "id"
      ],
      "sourceColumns": [
        "track_id"
      ]
    },
    {
      "targetTable": "event",
      "sourceTable": "track",
      "targetColumns": [
        "id"
      ],
      "sourceColumns": [
        "event_id"
      ]
    },
    {
      "targetTable": "event",
      "sourceTable": "booth_discussion_group",
      "targetColumns": [
        "id"
      ],
      "sourceColumns": [
        "event_id"
      ]
    },
    {
      "targetTable": "booth",
      "sourceTable": "booth_discussion_group",
      "targetColumns": [
        "id"
      ],
      "sourceColumns": [
        "booth_id"
      ]
    },
    {
      "targetTable": "event",
      "sourceTable": "booth_resource",
      "targetColumns": [
        "id"
      ],
      "sourceColumns": [
        "event_id"
      ]
    },
    {
      "targetTable": "booth",
      "sourceTable": "booth_resource",
      "targetColumns": [
        "id"
      ],
      "sourceColumns": [
        "booth_id"
      ]
    },
    {
      "targetTable": "event",
      "sourceTable": "booth",
      "targetColumns": [
        "id"
      ],
      "sourceColumns": [
        "event_id"
      ]
    },
    {
      "targetTable": "event_speaker",
      "sourceTable": "broadcast_speaker",
      "targetColumns": [
        "id"
      ],
      "sourceColumns": [
        "speaker_id"
      ]
    },
    {
      "targetTable": "broadcast",
      "sourceTable": "broadcast_speaker",
      "targetColumns": [
        "id"
      ],
      "sourceColumns": [
        "broadcast_id"
      ]
    },
    {
      "targetTable": "broadcast",
      "sourceTable": "broadcast_speaker",
      "targetColumns": [
        "event_id"
      ],
      "sourceColumns": [
        "event_id"
      ]
    },
    {
      "targetTable": "broadcast",
      "sourceTable": "broadcast_video_asset",
      "targetColumns": [
        "id"
      ],
      "sourceColumns": [
        "broadcast_id"
      ]
    },
    {
      "targetTable": "broadcast",
      "sourceTable": "broadcast_video_asset",
      "targetColumns": [
        "event_id"
      ],
      "sourceColumns": [
        "event_id"
      ]
    },
    {
      "targetTable": "organization",
      "sourceTable": "broadcast",
      "targetColumns": [
        "id"
      ],
      "sourceColumns": [
        "organization"
      ]
    },
    {
      "targetTable": "organization",
      "sourceTable": "tag_library",
      "targetColumns": [
        "id"
      ],
      "sourceColumns": [
        "organization"
      ]
    },
    {
      "targetTable": "event",
      "sourceTable": "event_member",
      "targetColumns": [
        "id"
      ],
      "sourceColumns": [
        "event_id"
      ]
    },
    {
      "targetTable": "track",
      "sourceTable": "event_member",
      "targetColumns": [
        "id"
      ],
      "sourceColumns": [
        "track_id"
      ]
    },
    {
      "targetTable": "event",
      "sourceTable": "resource",
      "targetColumns": [
        "id"
      ],
      "sourceColumns": [
        "event_id"
      ]
    }
  ],
  "positions": {
    "ticket_type": {
      "x": 1927.0,
      "y": 3981.0
    },
    "broadcast": {
      "x": -431.0,
      "y": 2957.0
    },
    "broadcast_chapter": {
      "x": -1232.0,
      "y": 5537.0
    },
    "event_member": {
      "x": 1685.0,
      "y": 416.0
    },
    "a785c95c8e": {
      "x": -544.0,
      "y": 1388.0
    },
    "event_form_field": {
      "x": 64.0,
      "y": 64.0
    },
    "ticket_type_allowed_track": {
      "x": 2549.0,
      "y": 4541.0
    },
    "broadcast_speaker": {
      "x": -1856.0,
      "y": 4933.0
    },
    "broadcast_on_demand_asset_chapter": {
      "x": -1232.0,
      "y": 4627.0
    },
    "broadcast_staff": {
      "x": -1856.0,
      "y": 5371.0
    },
    "event": {
      "x": 820.0,
      "y": -46.0
    },
    "public_agenda_session_speaker": {
      "x": -1947.0,
      "y": 99.0
    },
    "track": {
      "x": 1927.0,
      "y": 4872.0
    },
    "broadcast_video_asset": {
      "x": -2595.0,
      "y": 4073.0
    },
    "broadcast_resource": {
      "x": -1232.0,
      "y": 5107.0
    },
    "booth_discussion_group_object": {
      "x": -2730.0,
      "y": 873.0
    },
    "public_agenda": {
      "x": -1427.0,
      "y": 99.0
    },
    "tag_library": {
      "x": 2481.0,
      "y": 2821.0
    },
    "resource": {
      "x": 544.0,
      "y": 416.0
    },
    "event_supported_language": {
      "x": 544.0,
      "y": 64.0
    },
    "event_form_id_list": {
      "x": 64.0,
      "y": 668.0
    },
    "event_speaker": {
      "x": -1209.0,
      "y": 1057.0
    },
    "booth": {
      "x": -2017.0,
      "y": 1686.0
    },
    "agenda_item": {
      "x": -753.0,
      "y": 99.0
    },
    "booth_resources": {
      "x": -2730.0,
      "y": 2233.0
    },
    "organization": {
      "x": 2430.0,
      "y": -65.0
    }
  },
  "notes": {
    "byTable": {},
    "generalNotes": []
  },
  "tableGroups": [
    {
      "id": "a785c95c8e",
      "parentTable": "event",
      "tables": [
        "agenda_item",
        "event_form_field",
        "resource",
        "event_supported_language"
      ],
      "excludedTables": [],
      "width": null,
      "height": null
    }
  ]
}