{
  "tables": [
    {
      "name": "training_enrollment",
      "columns": [
        {
          "name": "id",
          "type": "Unknown",
          "primaryKey": true
        },
        {
          "name": "email_address",
          "type": "Unknown",
          "foreignKey": true
        },
        {
          "name": "assignment_creation",
          "type": "Unknown"
        },
        {
          "name": "assignment_due_date",
          "type": "Unknown"
        },
        {
          "name": "assignment_id",
          "type": "Unknown"
        },
        {
          "name": "assignment_name",
          "type": "Unknown"
        },
        {
          "name": "assignment_start_date",
          "type": "Unknown"
        },
        {
          "name": "assignment_type",
          "type": "Unknown"
        },
        {
          "name": "enrollment_removal_date",
          "type": "Unknown"
        },
        {
          "name": "enrollment_removal_reason",
          "type": "Unknown"
        },
        {
          "name": "is_auto_enroll",
          "type": "Unknown"
        },
        {
          "name": "manager_emailaddress",
          "type": "Unknown"
        },
        {
          "name": "module_attempt_status",
          "type": "Unknown"
        },
        {
          "name": "module_due_date",
          "type": "Unknown"
        },
        {
          "name": "module_enrollment_date",
          "type": "Unknown"
        },
        {
          "name": "module_id",
          "type": "Unknown"
        },
        {
          "name": "module_name_admin",
          "type": "Unknown"
        },
        {
          "name": "module_name_user",
          "type": "Unknown"
        },
        {
          "name": "user_assignment_completion_date_time",
          "type": "Unknown"
        },
        {
          "name": "user_assignment_status",
          "type": "Unknown"
        },
        {
          "name": "user_module_completion_date_time",
          "type": "Unknown"
        }
      ],
      "tags": [],
      "link": "https://proofpoint.securityeducation.com/api/reporting/documentation/#api-API_Endpoints-TrainingEnrollmentsFunction"
    },
    {
      "name": "phish_alarm",
      "columns": [
        {
          "name": "_fivetran_id",
          "type": "String",
          "primaryKey": true
        },
        {
          "name": "email_address",
          "type": "Unknown",
          "foreignKey": true
        },
        {
          "name": "action",
          "type": "Unknown"
        },
        {
          "name": "assessment_soft_deleted_date",
          "type": "Unknown"
        },
        {
          "name": "campaign_name",
          "type": "Unknown"
        },
        {
          "name": "elapsed_hour",
          "type": "Unknown"
        },
        {
          "name": "email_client_version",
          "type": "Unknown"
        },
        {
          "name": "emailtype",
          "type": "Unknown"
        },
        {
          "name": "id",
          "type": "Unknown"
        },
        {
          "name": "os",
          "type": "Unknown"
        },
        {
          "name": "received_date",
          "type": "Unknown"
        },
        {
          "name": "reported_date",
          "type": "Unknown"
        }
      ],
      "tags": [],
      "link": "https://proofpoint.securityeducation.com/api/reporting/documentation/#api-API_Endpoints-PhishAlarmFunction"
    },
    {
      "name": "knowledge_assessment",
      "columns": [
        {
          "name": "_fivetran_id",
          "type": "String",
          "primaryKey": true
        },
        {
          "name": "email_address",
          "type": "Unknown",
          "foreignKey": true
        },
        {
          "name": "assessment_name",
          "type": "Unknown"
        },
        {
          "name": "assessment_status",
          "type": "Unknown"
        },
        {
          "name": "assessment_type",
          "type": "Unknown"
        },
        {
          "name": "assignment_average_score",
          "type": "Unknown"
        },
        {
          "name": "assignment_deleted_date",
          "type": "Unknown"
        },
        {
          "name": "assignment_due_date",
          "type": "Unknown"
        },
        {
          "name": "assignment_name",
          "type": "Unknown"
        },
        {
          "name": "assignment_start_date",
          "type": "Unknown"
        },
        {
          "name": "assignment_status",
          "type": "Unknown"
        },
        {
          "name": "attempt_date",
          "type": "Unknown"
        },
        {
          "name": "category",
          "type": "Unknown"
        },
        {
          "name": "category_benchmark_all",
          "type": "Unknown"
        },
        {
          "name": "category_benchmark_industry",
          "type": "Unknown"
        },
        {
          "name": "company_average_score",
          "type": "Unknown"
        },
        {
          "name": "correct",
          "type": "Unknown"
        },
        {
          "name": "id",
          "type": "Unknown"
        },
        {
          "name": "is_ae_enabled",
          "type": "Unknown"
        },
        {
          "name": "is_custom_question",
          "type": "Unknown"
        },
        {
          "name": "question_date",
          "type": "Unknown"
        },
        {
          "name": "question_id",
          "type": "Unknown"
        },
        {
          "name": "question_latency",
          "type": "Unknown"
        },
        {
          "name": "question_text",
          "type": "Unknown"
        },
        {
          "name": "question_type",
          "type": "Unknown"
        },
        {
          "name": "questions_in_category",
          "type": "Unknown"
        },
        {
          "name": "seconds_in_attempt",
          "type": "Unknown"
        },
        {
          "name": "selected_answer",
          "type": "Unknown"
        },
        {
          "name": "user_answered_on_assignment",
          "type": "Unknown"
        },
        {
          "name": "user_assignment_status",
          "type": "Unknown"
        },
        {
          "name": "user_correcton_assignment",
          "type": "Unknown"
        },
        {
          "name": "user_removed_from_assignment",
          "type": "Unknown"
        },
        {
          "name": "user_score_on_assignment",
          "type": "Unknown"
        }
      ],
      "tags": [],
      "link": "https://proofpoint.securityeducation.com/api/reporting/documentation/#api-API_Endpoints-CyberStrengthFunction"
    },
    {
      "name": "phishing_extended",
      "columns": [
        {
          "name": "_fivetran_id",
          "type": "String",
          "primaryKey": true
        },
        {
          "name": "email_address",
          "type": "Unknown",
          "foreignKey": true
        },
        {
          "name": "afr",
          "type": "Unknown"
        },
        {
          "name": "assessment_is_archived",
          "type": "Unknown"
        },
        {
          "name": "auto_enrollment",
          "type": "Unknown"
        },
        {
          "name": "browser",
          "type": "Unknown"
        },
        {
          "name": "browser_version",
          "type": "Unknown"
        },
        {
          "name": "campaign_end_date",
          "type": "Unknown"
        },
        {
          "name": "campaign_guid",
          "type": "Unknown"
        },
        {
          "name": "campaign_name",
          "type": "Unknown"
        },
        {
          "name": "campaign_start_date",
          "type": "Unknown"
        },
        {
          "name": "campaign_status",
          "type": "Unknown"
        },
        {
          "name": "campaign_type",
          "type": "Unknown"
        },
        {
          "name": "event_timestamp",
          "type": "Unknown"
        },
        {
          "name": "event_type",
          "type": "Unknown"
        },
        {
          "name": "id",
          "type": "Unknown"
        },
        {
          "name": "ip_address",
          "type": "Unknown"
        },
        {
          "name": "mobile_device_used",
          "type": "Unknown"
        },
        {
          "name": "os",
          "type": "Unknown"
        },
        {
          "name": "os_version",
          "type": "Unknown"
        },
        {
          "name": "sent_timestamp",
          "type": "Unknown"
        },
        {
          "name": "template_name",
          "type": "Unknown"
        },
        {
          "name": "template_subject",
          "type": "Unknown"
        },
        {
          "name": "user_agent",
          "type": "Unknown"
        },
        {
          "name": "user_guid",
          "type": "Unknown"
        },
        {
          "name": "who_is_city",
          "type": "Unknown"
        },
        {
          "name": "who_is_continent",
          "type": "Unknown"
        },
        {
          "name": "who_is_country",
          "type": "Unknown"
        },
        {
          "name": "who_is_domain",
          "type": "Unknown"
        },
        {
          "name": "who_is_isp",
          "type": "Unknown"
        },
        {
          "name": "who_is_latitude",
          "type": "Unknown"
        },
        {
          "name": "who_is_longitude",
          "type": "Unknown"
        },
        {
          "name": "who_is_organization",
          "type": "Unknown"
        },
        {
          "name": "who_is_state",
          "type": "Unknown"
        }
      ],
      "tags": [],
      "link": "https://proofpoint.securityeducation.com/api/reporting/documentation/#api-API_Endpoints-PhishingExtendedEventFunction"
    },
    {
      "name": "users",
      "columns": [
        {
          "name": "email_address",
          "type": "Unknown",
          "primaryKey": true
        },
        {
          "name": "activeflag",
          "type": "Unknown"
        },
        {
          "name": "data_last_updated",
          "type": "Unknown"
        },
        {
          "name": "deleted_date",
          "type": "Unknown"
        },
        {
          "name": "first_name",
          "type": "Unknown"
        },
        {
          "name": "id",
          "type": "Unknown"
        },
        {
          "name": "last_name",
          "type": "Unknown"
        },
        {
          "name": "locale",
          "type": "Unknown"
        },
        {
          "name": "sso_id",
          "type": "Unknown"
        },
        {
          "name": "tags",
          "type": "Unknown"
        },
        {
          "name": "timezone",
          "type": "Unknown"
        }
      ],
      "tags": [],
      "link": "https://proofpoint.securityeducation.com/api/reporting/documentation/#api-API_Endpoints-UsersFunction"
    },
    {
      "name": "phishing",
      "columns": [
        {
          "name": "_fivetran_id",
          "type": "String",
          "primaryKey": true
        },
        {
          "name": "email_address",
          "type": "Unknown",
          "foreignKey": true
        },
        {
          "name": "assessment_is_archived",
          "type": "Unknown"
        },
        {
          "name": "auto_enrollment",
          "type": "Unknown"
        },
        {
          "name": "campaign_end_date",
          "type": "Unknown"
        },
        {
          "name": "campaign_name",
          "type": "Unknown"
        },
        {
          "name": "campaign_start_date",
          "type": "Unknown"
        },
        {
          "name": "campaign_status",
          "type": "Unknown"
        },
        {
          "name": "campaign_type",
          "type": "Unknown"
        },
        {
          "name": "event_timestamp",
          "type": "Unknown"
        },
        {
          "name": "event_type",
          "type": "Unknown"
        },
        {
          "name": "id",
          "type": "Unknown"
        },
        {
          "name": "sent_timestamp",
          "type": "Unknown"
        },
        {
          "name": "template_name",
          "type": "Unknown"
        },
        {
          "name": "template_subject",
          "type": "Unknown"
        }
      ],
      "tags": [],
      "link": "https://proofpoint.securityeducation.com/api/reporting/documentation/#api-API_Endpoints-PhishingEventFunction"
    },
    {
      "name": "training",
      "columns": [
        {
          "name": "_fivetran_id",
          "type": "String",
          "primaryKey": true
        },
        {
          "name": "email_address",
          "type": "Unknown",
          "foreignKey": true
        },
        {
          "name": "assignment_deleted",
          "type": "Unknown"
        },
        {
          "name": "assignment_deleted_date",
          "type": "Unknown"
        },
        {
          "name": "assignment_due_date",
          "type": "Unknown"
        },
        {
          "name": "assignment_method",
          "type": "Unknown"
        },
        {
          "name": "assignment_name",
          "type": "Unknown"
        },
        {
          "name": "assignment_start_date",
          "type": "Unknown"
        },
        {
          "name": "assignment_status",
          "type": "Unknown"
        },
        {
          "name": "duration",
          "type": "Unknown"
        },
        {
          "name": "force_completed_date",
          "type": "Unknown"
        },
        {
          "name": "id",
          "type": "Unknown"
        },
        {
          "name": "is_auto_enroll",
          "type": "Unknown"
        },
        {
          "name": "is_free_play",
          "type": "Unknown"
        },
        {
          "name": "module_attempt_date",
          "type": "Unknown"
        },
        {
          "name": "module_attempt_end_status",
          "type": "Unknown"
        },
        {
          "name": "module_attempt_score",
          "type": "Unknown"
        },
        {
          "name": "module_attempt_score_answered",
          "type": "Unknown"
        },
        {
          "name": "module_attempt_score_correct",
          "type": "Unknown"
        },
        {
          "name": "module_attempt_status",
          "type": "Unknown"
        },
        {
          "name": "module_last_action",
          "type": "Unknown"
        },
        {
          "name": "module_name_admin",
          "type": "Unknown"
        },
        {
          "name": "module_name_user",
          "type": "Unknown"
        },
        {
          "name": "module_type",
          "type": "Unknown"
        },
        {
          "name": "seconds_in_module_attempt",
          "type": "Unknown"
        },
        {
          "name": "user_assignment_status",
          "type": "Unknown"
        },
        {
          "name": "user_removed_from_assignment",
          "type": "Unknown"
        }
      ],
      "tags": [],
      "link": "https://proofpoint.securityeducation.com/api/reporting/documentation/#api-API_Endpoints-TrainingFunction"
    }
  ],
  "relations": [
    {
      "targetTable": "users",
      "sourceTable": "training_enrollment",
      "targetColumns": [
        "email_address"
      ],
      "sourceColumns": [
        "email_address"
      ]
    },
    {
      "targetTable": "users",
      "sourceTable": "phish_alarm",
      "targetColumns": [
        "email_address"
      ],
      "sourceColumns": [
        "email_address"
      ]
    },
    {
      "targetTable": "users",
      "sourceTable": "knowledge_assessment",
      "targetColumns": [
        "email_address"
      ],
      "sourceColumns": [
        "email_address"
      ]
    },
    {
      "targetTable": "users",
      "sourceTable": "phishing_extended",
      "targetColumns": [
        "email_address"
      ],
      "sourceColumns": [
        "email_address"
      ]
    },
    {
      "targetTable": "users",
      "sourceTable": "phishing",
      "targetColumns": [
        "email_address"
      ],
      "sourceColumns": [
        "email_address"
      ]
    },
    {
      "targetTable": "users",
      "sourceTable": "training",
      "targetColumns": [
        "email_address"
      ],
      "sourceColumns": [
        "email_address"
      ]
    }
  ],
  "positions": {
    "phish_alram": {
      "x": 504.0,
      "y": 0.0
    },
    "phishing": {
      "x": 505.55155681056317,
      "y": 596.9688637887399
    },
    "phishing_extentend": {
      "x": 1008.0,
      "y": 0.0
    },
    "training": {
      "x": 1512.0,
      "y": 0.0
    },
    "users": {
      "x": 1006.2583295724532,
      "y": -479.4435906957642
    },
    "training_enrollement": {
      "x": 2016.0,
      "y": 0.0
    },
    "knowledge_assesment": {
      "x": 34.13424983238622,
      "y": 10.860897673941054
    }
  },
  "notes": {
    "byTable": {},
    "generalNotes": []
  },
  "tableGroups": [
    {
      "id": "b51cbf7ffd",
      "parentTable": "users",
      "tables": [
        "phishing",
        "training_enrollment",
        "phish_alarm",
        "phishing_extended",
        "training",
        "knowledge_assessment"
      ],
      "excludedTables": [],
      "width": null,
      "height": null
    }
  ]
}