{
  "tables": [
    {
      "name": "waitlist_variant",
      "columns": [
        {
          "name": "index",
          "type": "Unknown",
          "primaryKey": true
        },
        {
          "name": "waitlist_id",
          "type": "Unknown",
          "primaryKey": true,
          "foreignKey": true
        },
        {
          "name": "available",
          "type": "Unknown"
        },
        {
          "name": "buy_size",
          "type": "Unknown"
        },
        {
          "name": "committed",
          "type": "Unknown"
        },
        {
          "name": "sku",
          "type": "Unknown"
        },
        {
          "name": "variant_id",
          "type": "Unknown"
        }
      ],
      "tags": [],
      "link": "https://docs.getpurpledot.com/docs/platform-integration-references/private-api/waitlists"
    },
    {
      "name": "waitlist",
      "columns": [
        {
          "name": "id",
          "type": "Unknown",
          "primaryKey": true
        },
        {
          "name": "availability_product_available",
          "type": "Unknown"
        },
        {
          "name": "availability_product_buy_size",
          "type": "Unknown"
        },
        {
          "name": "availability_product_committed",
          "type": "Unknown"
        },
        {
          "name": "availability_product_id",
          "type": "Unknown"
        },
        {
          "name": "created_at",
          "type": "Unknown"
        },
        {
          "name": "earliest_ship_date",
          "type": "Unknown"
        },
        {
          "name": "labels",
          "type": "Json"
        },
        {
          "name": "latest_ship_date",
          "type": "Unknown"
        },
        {
          "name": "launch_date",
          "type": "Unknown"
        },
        {
          "name": "state",
          "type": "Unknown"
        },
        {
          "name": "updated_at_min",
          "type": "Unknown"
        }
      ],
      "tags": [],
      "link": null
    },
    {
      "name": "pre_order_count_unit_sku",
      "columns": [
        {
          "name": "sku",
          "type": "Unknown",
          "primaryKey": true
        },
        {
          "name": "at_time",
          "type": "Unknown"
        },
        {
          "name": "canceled_units",
          "type": "Unknown"
        },
        {
          "name": "exported_units",
          "type": "Unknown"
        },
        {
          "name": "open_units",
          "type": "Unknown"
        }
      ],
      "tags": [],
      "link": "https://docs.getpurpledot.com/docs/platform-integration-references/private-api/pre-orders-count-units-sku-sku"
    },
    {
      "name": "fullfillement_order_line_item_tax",
      "columns": [
        {
          "name": "index",
          "type": "Unknown",
          "primaryKey": true
        },
        {
          "name": "fulfillment_order_id",
          "type": "Unknown",
          "primaryKey": true,
          "foreignKey": true
        },
        {
          "name": "fulfillment_order_line_item_index",
          "type": "Unknown",
          "primaryKey": true,
          "foreignKey": true
        },
        {
          "name": "price",
          "type": "Unknown"
        },
        {
          "name": "rate",
          "type": "Unknown"
        },
        {
          "name": "title",
          "type": "Unknown"
        }
      ],
      "tags": [],
      "link": "https://docs.getpurpledot.com/docs/platform-integration-references/private-api/fulfillment-orders"
    },
    {
      "name": "fulfillment_order_line_item",
      "columns": [
        {
          "name": "index",
          "type": "Unknown",
          "primaryKey": true
        },
        {
          "name": "fulfillment_order_id",
          "type": "Unknown",
          "primaryKey": true,
          "foreignKey": true
        },
        {
          "name": "id",
          "type": "Unknown"
        },
        {
          "name": "name",
          "type": "Unknown"
        },
        {
          "name": "price",
          "type": "Unknown"
        },
        {
          "name": "product_id",
          "type": "Unknown"
        },
        {
          "name": "quantity",
          "type": "Unknown"
        },
        {
          "name": "sku",
          "type": "Unknown"
        },
        {
          "name": "taxable",
          "type": "Unknown"
        },
        {
          "name": "total",
          "type": "Unknown"
        },
        {
          "name": "total_discount",
          "type": "Unknown"
        },
        {
          "name": "variant_id",
          "type": "Unknown"
        }
      ],
      "tags": [],
      "link": "https://docs.getpurpledot.com/docs/platform-integration-references/private-api/fulfillment-orders"
    },
    {
      "name": "fullfillement_order_shipping_line_tax",
      "columns": [
        {
          "name": "index",
          "type": "Unknown",
          "primaryKey": true
        },
        {
          "name": "fulfillment_order_id",
          "type": "Unknown",
          "primaryKey": true,
          "foreignKey": true
        },
        {
          "name": "fulfillment_order_shipping_line_index",
          "type": "Unknown",
          "primaryKey": true,
          "foreignKey": true
        },
        {
          "name": "price",
          "type": "Unknown"
        },
        {
          "name": "rate",
          "type": "Unknown"
        },
        {
          "name": "title",
          "type": "Unknown"
        }
      ],
      "tags": [],
      "link": "https://docs.getpurpledot.com/docs/platform-integration-references/private-api/fulfillment-orders"
    },
    {
      "name": "fulfillment_order_shipping_line",
      "columns": [
        {
          "name": "index",
          "type": "Unknown",
          "primaryKey": true
        },
        {
          "name": "fulfillment_order_id",
          "type": "Unknown",
          "primaryKey": true,
          "foreignKey": true
        },
        {
          "name": "code",
          "type": "Unknown"
        },
        {
          "name": "id",
          "type": "Unknown"
        },
        {
          "name": "price",
          "type": "Unknown"
        },
        {
          "name": "title",
          "type": "Unknown"
        },
        {
          "name": "total",
          "type": "Unknown"
        }
      ],
      "tags": [],
      "link": "https://docs.getpurpledot.com/docs/platform-integration-references/private-api/fulfillment-orders"
    },
    {
      "name": "fulfillment_order",
      "columns": [
        {
          "name": "id",
          "type": "Unknown",
          "primaryKey": true
        },
        {
          "name": "created_at",
          "type": "Instant"
        },
        {
          "name": "currency",
          "type": "Unknown"
        },
        {
          "name": "customer_default_address_address_1",
          "type": "Unknown"
        },
        {
          "name": "customer_default_address_address_2",
          "type": "Unknown"
        },
        {
          "name": "customer_default_address_city",
          "type": "Unknown"
        },
        {
          "name": "customer_default_address_country",
          "type": "Unknown"
        },
        {
          "name": "customer_default_address_country_code",
          "type": "Unknown"
        },
        {
          "name": "customer_default_address_first_name",
          "type": "Unknown"
        },
        {
          "name": "customer_default_address_last_name",
          "type": "Unknown"
        },
        {
          "name": "customer_default_address_phone",
          "type": "Unknown"
        },
        {
          "name": "customer_default_address_postal_code",
          "type": "Unknown"
        },
        {
          "name": "customer_default_address_province_code",
          "type": "Unknown"
        },
        {
          "name": "customer_email",
          "type": "Unknown"
        },
        {
          "name": "customer_external_id",
          "type": "Unknown"
        },
        {
          "name": "customer_first_name",
          "type": "Unknown"
        },
        {
          "name": "customer_last_name",
          "type": "Unknown"
        },
        {
          "name": "customer_tags",
          "type": "Json"
        },
        {
          "name": "note",
          "type": "Unknown"
        },
        {
          "name": "purchased_at",
          "type": "Unknown"
        },
        {
          "name": "reference",
          "type": "Unknown"
        },
        {
          "name": "shipping_address_address_1",
          "type": "Unknown"
        },
        {
          "name": "shipping_address_address_2",
          "type": "Unknown"
        },
        {
          "name": "shipping_address_city",
          "type": "Unknown"
        },
        {
          "name": "shipping_address_country",
          "type": "Unknown"
        },
        {
          "name": "shipping_address_country_code",
          "type": "Unknown"
        },
        {
          "name": "shipping_address_first_name",
          "type": "Unknown"
        },
        {
          "name": "shipping_address_last_name",
          "type": "Unknown"
        },
        {
          "name": "shipping_address_phone",
          "type": "Unknown"
        },
        {
          "name": "shipping_address_postal_code",
          "type": "Unknown"
        },
        {
          "name": "shipping_address_province_code",
          "type": "Unknown"
        },
        {
          "name": "subtotal_price",
          "type": "Unknown"
        },
        {
          "name": "tax_included",
          "type": "Unknown"
        },
        {
          "name": "total_discounts",
          "type": "Unknown"
        },
        {
          "name": "total_price",
          "type": "Unknown"
        },
        {
          "name": "total_tax",
          "type": "Unknown"
        }
      ],
      "tags": [],
      "link": "https://docs.getpurpledot.com/docs/platform-integration-references/private-api/fulfillment-orders"
    },
    {
      "name": "pre_order_line_item_tax",
      "columns": [
        {
          "name": "index",
          "type": "Unknown",
          "primaryKey": true
        },
        {
          "name": "pre_order_id",
          "type": "Unknown",
          "primaryKey": true,
          "foreignKey": true
        },
        {
          "name": "pre_order_line_item_index",
          "type": "Unknown",
          "primaryKey": true,
          "foreignKey": true
        },
        {
          "name": "inclusive",
          "type": "Unknown"
        },
        {
          "name": "price",
          "type": "Unknown"
        },
        {
          "name": "rate",
          "type": "Unknown"
        },
        {
          "name": "title",
          "type": "Unknown"
        }
      ],
      "tags": [],
      "link": "https://docs.getpurpledot.com/docs/platform-integration-references/private-api/pre-orders"
    },
    {
      "name": "pre_order_line_item",
      "columns": [
        {
          "name": "index",
          "type": "Unknown",
          "primaryKey": true
        },
        {
          "name": "pre_order_id",
          "type": "Unknown",
          "primaryKey": true,
          "foreignKey": true
        },
        {
          "name": "cancelled",
          "type": "Unknown"
        },
        {
          "name": "cancelled_at",
          "type": "Unknown"
        },
        {
          "name": "discount_allocations",
          "type": "Json"
        },
        {
          "name": "earliest_ship_date",
          "type": "Unknown"
        },
        {
          "name": "id",
          "type": "Unknown"
        },
        {
          "name": "latest_ship_date",
          "type": "Unknown"
        },
        {
          "name": "name",
          "type": "Unknown"
        },
        {
          "name": "price",
          "type": "Unknown"
        },
        {
          "name": "product_id",
          "type": "Unknown"
        },
        {
          "name": "quantity",
          "type": "Unknown"
        },
        {
          "name": "shopify_line_item_id",
          "type": "Unknown"
        },
        {
          "name": "sku",
          "type": "Unknown"
        },
        {
          "name": "taxable",
          "type": "Unknown"
        },
        {
          "name": "total",
          "type": "Unknown"
        },
        {
          "name": "total_discount",
          "type": "Unknown"
        },
        {
          "name": "unit_price",
          "type": "Unknown"
        },
        {
          "name": "unit_total",
          "type": "Unknown"
        },
        {
          "name": "variant_id",
          "type": "Unknown"
        }
      ],
      "tags": [],
      "link": "https://docs.getpurpledot.com/docs/platform-integration-references/private-api/pre-orders"
    },
    {
      "name": "pre_order_tax_line",
      "columns": [
        {
          "name": "index",
          "type": "Unknown",
          "primaryKey": true
        },
        {
          "name": "pre_order_id",
          "type": "Unknown",
          "primaryKey": true,
          "foreignKey": true
        },
        {
          "name": "price",
          "type": "Unknown"
        },
        {
          "name": "rate",
          "type": "Unknown"
        },
        {
          "name": "title",
          "type": "Unknown"
        }
      ],
      "tags": [],
      "link": "https://docs.getpurpledot.com/docs/platform-integration-references/private-api/pre-orders"
    },
    {
      "name": "pre_order_shipping_line_discount_allocation",
      "columns": [
        {
          "name": "index",
          "type": "Unknown",
          "primaryKey": true
        },
        {
          "name": "pre_order_id",
          "type": "Unknown",
          "primaryKey": true,
          "foreignKey": true
        },
        {
          "name": "pre_order_shipping_line_index",
          "type": "Unknown",
          "primaryKey": true,
          "foreignKey": true
        },
        {
          "name": "amount",
          "type": "Unknown"
        },
        {
          "name": "discount_application_index",
          "type": "Unknown"
        }
      ],
      "tags": [],
      "link": "https://docs.getpurpledot.com/docs/platform-integration-references/private-api/pre-orders"
    },
    {
      "name": "pre_order_shipping_line_tax",
      "columns": [
        {
          "name": "index",
          "type": "Unknown",
          "primaryKey": true
        },
        {
          "name": "pre_order_id",
          "type": "Unknown",
          "primaryKey": true,
          "foreignKey": true
        },
        {
          "name": "pre_order_shipping_line_index",
          "type": "Unknown",
          "primaryKey": true,
          "foreignKey": true
        },
        {
          "name": "inclusive",
          "type": "Unknown"
        },
        {
          "name": "price",
          "type": "Unknown"
        },
        {
          "name": "rate",
          "type": "Unknown"
        },
        {
          "name": "title",
          "type": "Unknown"
        }
      ],
      "tags": [],
      "link": "https://docs.getpurpledot.com/docs/platform-integration-references/private-api/pre-orders"
    },
    {
      "name": "pre_order_shipping_line_item",
      "columns": [
        {
          "name": "index",
          "type": "Unknown",
          "primaryKey": true
        },
        {
          "name": "pre_order_id",
          "type": "Unknown",
          "primaryKey": true,
          "foreignKey": true
        },
        {
          "name": "pre_order_shipping_line_index",
          "type": "Unknown",
          "primaryKey": true,
          "foreignKey": true
        },
        {
          "name": "line_item_id",
          "type": "Unknown"
        }
      ],
      "tags": [],
      "link": "https://docs.getpurpledot.com/docs/platform-integration-references/private-api/pre-orders"
    },
    {
      "name": "pre_order_shipping_line",
      "columns": [
        {
          "name": "index",
          "type": "Unknown",
          "primaryKey": true
        },
        {
          "name": "pre_order_id",
          "type": "Unknown",
          "primaryKey": true,
          "foreignKey": true
        },
        {
          "name": "code",
          "type": "Unknown"
        },
        {
          "name": "price",
          "type": "Unknown"
        },
        {
          "name": "title",
          "type": "Unknown"
        },
        {
          "name": "total",
          "type": "Unknown"
        }
      ],
      "tags": [],
      "link": "https://docs.getpurpledot.com/docs/platform-integration-references/private-api/pre-orders"
    },
    {
      "name": "pre_order_exported_line_item",
      "columns": [
        {
          "name": "index",
          "type": "Unknown",
          "primaryKey": true
        },
        {
          "name": "pre_order_exported_index",
          "type": "Unknown",
          "primaryKey": true,
          "foreignKey": true
        },
        {
          "name": "pre_order_id",
          "type": "Unknown",
          "primaryKey": true,
          "foreignKey": true
        },
        {
          "name": "id",
          "type": "Unknown"
        },
        {
          "name": "line_item_id",
          "type": "Unknown"
        }
      ],
      "tags": [],
      "link": "https://docs.getpurpledot.com/docs/platform-integration-references/private-api/pre-orders"
    },
    {
      "name": "pre_order_exported",
      "columns": [
        {
          "name": "index",
          "type": "Unknown",
          "primaryKey": true
        },
        {
          "name": "pre_order_id",
          "type": "Unknown",
          "primaryKey": true,
          "foreignKey": true
        },
        {
          "name": "created_at",
          "type": "Unknown"
        },
        {
          "name": "id",
          "type": "Unknown"
        },
        {
          "name": "order_number",
          "type": "Unknown"
        },
        {
          "name": "type",
          "type": "Unknown"
        }
      ],
      "tags": [],
      "link": "https://docs.getpurpledot.com/docs/platform-integration-references/private-api/pre-orders"
    },
    {
      "name": "pre_order",
      "columns": [
        {
          "name": "id",
          "type": "Unknown",
          "primaryKey": true
        },
        {
          "name": "cancel_reason",
          "type": "Unknown"
        },
        {
          "name": "cancelled_at",
          "type": "Unknown"
        },
        {
          "name": "created_at",
          "type": "Unknown"
        },
        {
          "name": "currency",
          "type": "Unknown"
        },
        {
          "name": "customer_email",
          "type": "Unknown"
        },
        {
          "name": "customer_external_id",
          "type": "Unknown"
        },
        {
          "name": "discount_applications",
          "type": "Json"
        },
        {
          "name": "discount_codes",
          "type": "Json"
        },
        {
          "name": "email",
          "type": "Unknown"
        },
        {
          "name": "number",
          "type": "Unknown"
        },
        {
          "name": "reference",
          "type": "Unknown"
        },
        {
          "name": "shipping_address_address_1",
          "type": "Unknown"
        },
        {
          "name": "shipping_address_address_2",
          "type": "Unknown"
        },
        {
          "name": "shipping_address_city",
          "type": "Unknown"
        },
        {
          "name": "shipping_address_country",
          "type": "Unknown"
        },
        {
          "name": "shipping_address_country_code",
          "type": "Unknown"
        },
        {
          "name": "shipping_address_first_name",
          "type": "Unknown"
        },
        {
          "name": "shipping_address_last_name",
          "type": "Unknown"
        },
        {
          "name": "shipping_address_phone",
          "type": "Unknown"
        },
        {
          "name": "shipping_address_postal_code",
          "type": "Unknown"
        },
        {
          "name": "shipping_address_province_code",
          "type": "Unknown"
        },
        {
          "name": "subtotal_price",
          "type": "Unknown"
        },
        {
          "name": "tax_included",
          "type": "Unknown"
        },
        {
          "name": "total_discounts",
          "type": "Unknown"
        },
        {
          "name": "total_price",
          "type": "Unknown"
        },
        {
          "name": "total_refunded",
          "type": "Unknown"
        },
        {
          "name": "total_tax",
          "type": "Unknown"
        },
        {
          "name": "updated_at_min",
          "type": "Unknown"
        }
      ],
      "tags": [],
      "link": "https://docs.getpurpledot.com/docs/platform-integration-references/private-api/pre-orders"
    }
  ],
  "relations": [
    {
      "targetTable": "waitlist",
      "sourceTable": "waitlist_variant",
      "targetColumns": [
        "id"
      ],
      "sourceColumns": [
        "waitlist_id"
      ]
    },
    {
      "targetTable": "fulfillment_order",
      "sourceTable": "fullfillement_order_line_item_tax",
      "targetColumns": [
        "id"
      ],
      "sourceColumns": [
        "fulfillment_order_id"
      ]
    },
    {
      "targetTable": "fulfillment_order_line_item",
      "sourceTable": "fullfillement_order_line_item_tax",
      "targetColumns": [
        "index"
      ],
      "sourceColumns": [
        "fulfillment_order_line_item_index"
      ]
    },
    {
      "targetTable": "fulfillment_order",
      "sourceTable": "fulfillment_order_line_item",
      "targetColumns": [
        "id"
      ],
      "sourceColumns": [
        "fulfillment_order_id"
      ]
    },
    {
      "targetTable": "fulfillment_order",
      "sourceTable": "fullfillement_order_shipping_line_tax",
      "targetColumns": [
        "id"
      ],
      "sourceColumns": [
        "fulfillment_order_id"
      ]
    },
    {
      "targetTable": "fulfillment_order_shipping_line",
      "sourceTable": "fullfillement_order_shipping_line_tax",
      "targetColumns": [
        "index"
      ],
      "sourceColumns": [
        "fulfillment_order_shipping_line_index"
      ]
    },
    {
      "targetTable": "fulfillment_order",
      "sourceTable": "fulfillment_order_shipping_line",
      "targetColumns": [
        "id"
      ],
      "sourceColumns": [
        "fulfillment_order_id"
      ]
    },
    {
      "targetTable": "pre_order",
      "sourceTable": "pre_order_line_item_tax",
      "targetColumns": [
        "id"
      ],
      "sourceColumns": [
        "pre_order_id"
      ]
    },
    {
      "targetTable": "pre_order_line_item",
      "sourceTable": "pre_order_line_item_tax",
      "targetColumns": [
        "index"
      ],
      "sourceColumns": [
        "pre_order_line_item_index"
      ]
    },
    {
      "targetTable": "pre_order",
      "sourceTable": "pre_order_line_item",
      "targetColumns": [
        "id"
      ],
      "sourceColumns": [
        "pre_order_id"
      ]
    },
    {
      "targetTable": "pre_order",
      "sourceTable": "pre_order_tax_line",
      "targetColumns": [
        "id"
      ],
      "sourceColumns": [
        "pre_order_id"
      ]
    },
    {
      "targetTable": "pre_order",
      "sourceTable": "pre_order_shipping_line_discount_allocation",
      "targetColumns": [
        "id"
      ],
      "sourceColumns": [
        "pre_order_id"
      ]
    },
    {
      "targetTable": "pre_order_shipping_line",
      "sourceTable": "pre_order_shipping_line_discount_allocation",
      "targetColumns": [
        "index"
      ],
      "sourceColumns": [
        "pre_order_shipping_line_index"
      ]
    },
    {
      "targetTable": "pre_order",
      "sourceTable": "pre_order_shipping_line_tax",
      "targetColumns": [
        "id"
      ],
      "sourceColumns": [
        "pre_order_id"
      ]
    },
    {
      "targetTable": "pre_order_shipping_line",
      "sourceTable": "pre_order_shipping_line_tax",
      "targetColumns": [
        "index"
      ],
      "sourceColumns": [
        "pre_order_shipping_line_index"
      ]
    },
    {
      "targetTable": "pre_order",
      "sourceTable": "pre_order_shipping_line_item",
      "targetColumns": [
        "id"
      ],
      "sourceColumns": [
        "pre_order_id"
      ]
    },
    {
      "targetTable": "pre_order_shipping_line",
      "sourceTable": "pre_order_shipping_line_item",
      "targetColumns": [
        "index"
      ],
      "sourceColumns": [
        "pre_order_shipping_line_index"
      ]
    },
    {
      "targetTable": "pre_order",
      "sourceTable": "pre_order_shipping_line",
      "targetColumns": [
        "id"
      ],
      "sourceColumns": [
        "pre_order_id"
      ]
    },
    {
      "targetTable": "pre_order",
      "sourceTable": "pre_order_exported_line_item",
      "targetColumns": [
        "id"
      ],
      "sourceColumns": [
        "pre_order_id"
      ]
    },
    {
      "targetTable": "pre_order_exported",
      "sourceTable": "pre_order_exported_line_item",
      "targetColumns": [
        "index"
      ],
      "sourceColumns": [
        "pre_order_exported_index"
      ]
    },
    {
      "targetTable": "pre_order",
      "sourceTable": "pre_order_exported",
      "targetColumns": [
        "id"
      ],
      "sourceColumns": [
        "pre_order_id"
      ]
    }
  ],
  "positions": {
    "waitlist_variant": {
      "x": 3087.113758784525,
      "y": 2513.1248622603707
    },
    "waitlist": {
      "x": 3591.113758784525,
      "y": 2513.1248622603707
    },
    "pre_order_exported_line_item": {
      "x": 3825.094966892736,
      "y": 611.0116714020024
    },
    "pre_order_exported": {
      "x": 3825.094966892736,
      "y": 987.0116714020024
    },
    "fullfillement_order_line_item_tax": {
      "x": 1368,
      "y": 586
    },
    "fulfillment_order_line_item": {
      "x": 1872,
      "y": 586
    },
    "fullfillement_order_shipping_line_tax": {
      "x": 641,
      "y": 13
    },
    "fulfillment_order_shipping_line": {
      "x": 1145,
      "y": 13
    },
    "fulfillment_order": {
      "x": 641,
      "y": 461
    },
    "pre_order_line_item_tax": {
      "x": 2645.623747728494,
      "y": 1369.397427938306
    },
    "pre_order_line_item": {
      "x": 3149.623747728494,
      "y": 1369.397427938306
    },
    "pre_order_count_unit_sku": {
      "x": 1322.4266411140018,
      "y": 2488.0806815663636
    },
    "pre_order_tax_line": {
      "x": 2420.9117254718285,
      "y": 2470.0806815663636
    },
    "pre_order_shipping_line_discount_allocation": {
      "x": 1243.9634208027285,
      "y": 2858.4538076572117
    },
    "pre_order_shipping_line_tax": {
      "x": 1322,
      "y": 2000
    },
    "pre_order_shipping_line_item": {
      "x": 2420.9117254718285,
      "y": 2876.4538076572117
    },
    "pre_order_shipping_line": {
      "x": 2420.9117254718285,
      "y": 2035.966617897598
    },
    "pre_order": {
      "x": 1871.6691832929152,
      "y": 2028.3397439884461
    }
  },
  "notes": {
    "byTable": {},
    "generalNotes": []
  },
  "tableGroups": []
}